Record/__init__.py
Record/tests.py
Record-4.1.dist-info/LICENSE.txt
Record-4.1.dist-info/METADATA
Record-4.1.dist-info/WHEEL
Record-4.1.dist-info/top_level.txt
Record-4.1.dist-info/RECORD
